skidder/__init__.py
skidder/skidder.py
skidder-2020.2.14.dist-info/LICENSE.txt
skidder-2020.2.14.dist-info/METADATA
skidder-2020.2.14.dist-info/WHEEL
skidder-2020.2.14.dist-info/top_level.txt
skidder-2020.2.14.dist-info/RECORD
