Metadata-Version: 2.1
Name: skidder
Version: 2020.2.14
Summary: A Python logging library
Home-page: https://github.com/ktr/skidder
Author: Kevin Ryan
Author-email: ktr@26ocb.com
License: MIT
Project-URL: Bug Reports, https://github.com/ktr/skidder/issues
Project-URL: Source, https://github.com/ktr/skidder/
Keywords: logging
Platform: UNKNOWN
Classifier: Development Status :: 3 - Alpha
Classifier: Intended Audience :: Developers
Classifier: Topic :: Software Development :: Libraries
Classifier: Topic :: System :: Logging
Classifier: License :: OSI Approved :: MIT License
Classifier: Programming Language :: Python :: 3.8
